pyhumantime/__init__.py
pyhumantime/cli.py
pyhumantime/core.py
py_humantime-0.1.4.dist-info/METADATA
py_humantime-0.1.4.dist-info/WHEEL
py_humantime-0.1.4.dist-info/entry_points.txt
py_humantime-0.1.4.dist-info/top_level.txt
py_humantime-0.1.4.dist-info/RECORD
