Metadata-Version: 2.4
Name: py-humantime
Version: 0.1.4
Summary: Convert between seconds and human-readable time in CLI or code.
Author-email: Your Name <you@example.com>
Requires-Python: >=3.7
